nougatop/__init__.py
nougatop/displaytotext.py
nougatop/pdftotext.py
nougatop-0.1.0.dist-info/METADATA
nougatop-0.1.0.dist-info/WHEEL
nougatop-0.1.0.dist-info/top_level.txt
nougatop-0.1.0.dist-info/RECORD
